LICENSE.txt
MANIFEST.in
README.md
requirements-test.txt
requirements.txt
setup.cfg
setup.py
img/logo.png
padl/__init__.py
padl/exceptions.py
padl/print_utils.py
padl/transforms.py
padl/util_transforms.py
padl/utils.py
padl/version.py
padl/wrap.py
padl.egg-info/PKG-INFO
padl.egg-info/SOURCES.txt
padl.egg-info/dependency_links.txt
padl.egg-info/requires.txt
padl.egg-info/top_level.txt
padl/dumptools/__init__.py
padl/dumptools/ast_utils.py
padl/dumptools/config_tools.py
padl/dumptools/inspector.py
padl/dumptools/packagefinder.py
padl/dumptools/serialize.py
padl/dumptools/sourceget.py
padl/dumptools/symfinder.py
padl/dumptools/var2mod.py
tests/__init__.py
tests/fixtures/__init__.py
tests/fixtures/utils.py
tests/material/__init__.py
tests/material/find_codenode_from_import.py
tests/material/find_codenode_module_import.py
tests/material/long_list.py
tests/material/outer_caller.py
tests/material/outer_caller_1.py
tests/material/relative_import.py
tests/material/save_by_value.py
tests/material/transforms_in_module.py
tests/unittests/__init__.py
tests/unittests/test_dump.py
tests/unittests/test_thingfinder.py
tests/unittests/test_transforms.py
tests/unittests/test_util_transforms.py
tests/unittests/test_utils.py
tests/unittests/test_wrap.py
tests/unittests/transform_module.py
tests/unittests/dumptools/__init__.py
tests/unittests/dumptools/test_ast_utils.py
tests/unittests/dumptools/test_config_tools.py
tests/unittests/dumptools/test_inspector.py
tests/unittests/dumptools/test_packagefinder.py
tests/unittests/dumptools/test_serialize.py
tests/unittests/dumptools/test_sourceget.py
tests/unittests/dumptools/test_symfinder.py
tests/unittests/dumptools/test_var2mod.py