Metadata-Version: 2.1
Name: padl
Version: 0.2.6
Summary: Pipeline abstractions for deep learning
Home-page: https://github.com/lf1-io/padl
Author: LF1
Author-email: contact@lf1.io
License: Apache 2.0
Platform: UNKNOWN
Classifier: Programming Language :: Python :: 3.7
Classifier: Programming Language :: Python :: 3.8
Classifier: Programming Language :: Python :: 3.9
Classifier: Topic :: Scientific/Engineering
Classifier: Topic :: Scientific/Engineering :: Artificial Intelligence
Requires-Python: >=3.7
License-File: LICENSE.txt
